autowirter/__init__.py
autowriter-1.0.2.dist-info/METADATA
autowriter-1.0.2.dist-info/WHEEL
autowriter-1.0.2.dist-info/entry_points.txt
autowriter-1.0.2.dist-info/top_level.txt
autowriter-1.0.2.dist-info/RECORD
