Metadata-Version: 2.4
Name: autowriter
Version: 1.0.2
Summary: A human-like auto typer with GUI, dark mode, pause/wait keys, and live stats.
Home-page: https://github.com/Mysra-Ahmed/Python-auto-typer
Author: Mysra Ahmed
Author-email: misragmalahmad@gmail.com@email.com
Classifier: Programming Language :: Python :: 3
Classifier: Operating System :: OS Independent
Classifier: Topic :: Utilities
Requires-Python: >=3.6
Requires-Dist: keyboard
Dynamic: author
Dynamic: author-email
Dynamic: classifier
Dynamic: description
Dynamic: description-content-type
Dynamic: home-page
Dynamic: requires-dist
Dynamic: requires-python
Dynamic: summary
